{"shopLIst": [{"category": "Designer Fashions & Sportswear", "telephone": "D09", "store": "D09", "suit": "D09"}, {"category": "Designer Fashions & Sportswear", "telephone": "A12", "store": "A12", "suit": "A12"}, {"category": "Designer Fashions & Sportswear", "telephone": "E02", "store": "E02", "suit": "E02"}, {"category": "Designer Fashions & Sportswear", "telephone": "A11", "store": "A11", "suit": "A11"}, {"category": "Designer Fashions & Sportswear", "telephone": "H01A", "store": "H01A", "suit": "H01A"}, {"category": "Designer Fashions & Sportswear", "telephone": "H04", "store": "H04", "suit": "H04"}, {"category": "Designer Fashions & Sportswear", "telephone": "D02", "store": "D02", "suit": "D02"}, {"category": "Designer Fashions & Sportswear", "telephone": "F05", "store": "F05", "suit": "F05"}, {"category": "Designer Fashions & Sportswear", "telephone": "B01", "store": "B01", "suit": "B01"}, {"category": "Designer Fashions & Sportswear", "telephone": "B09", "store": "B09", "suit": "B09"}, {"category": "Designer Fashions & Sportswear", "telephone": "A19", "store": "A19", "suit": "A19"}, {"category": "Designer Fashions & Sportswear", "telephone": "A01", "store": "A01", "suit": "A01"}, {"category": "Designer Fashions & Sportswear", "telephone": "G13", "store": "G13", "suit": "G13"}, {"category": "Designer Fashions & Sportswear", "telephone": "C06", "store": "C06", "suit": "C06"}, {"category": "Designer Fashions & Sportswear", "telephone": "I01", "store": "I01", "suit": "I01"}, {"category": "Designer Fashions & Sportswear", "telephone": "000", "store": "000", "suit": "000"}, {"category": "Designer Fashions & Sportswear", "telephone": "G204", "store": "G204", "suit": "G204"}, {"category": "Designer Fashions & Sportswear", "telephone": "A14", "store": "A14", "suit": "A14"}, {"category": "Designer Fashions & Sportswear", "telephone": "A22", "store": "A22", "suit": "A22"}, {"category": "Designer Fashions & Sportswear", "telephone": "G08", "store": "G08", "suit": "G08"}, {"category": "Designer Fashions & Sportswear", "telephone": "G200", "store": "G200", "suit": "G200"}, {"category": "Designer Fashions & Sportswear", "telephone": "A08", "store": "A08", "suit": "A08"}, {"category": "Designer Fashions & Sportswear", "telephone": "G208", "store": "G208", "suit": "G208"}, {"category": "Designer Fashions & Sportswear", "telephone": "A05", "store": "A05", "suit": "A05"}, {"category": "Designer Fashions & Sportswear", "telephone": "A04", "store": "A04", "suit": "A04"}, {"category": "Designer Fashions & Sportswear", "telephone": "A02", "store": "A02", "suit": "A02"}, {"category": "Designer Fashions & Sportswear", "telephone": "A07", "store": "A07", "suit": "A07"}, {"category": "Designer Fashions & Sportswear", "telephone": "E04", "store": "E04", "suit": "E04"}, {"category": "Designer Fashions & Sportswear", "telephone": "G07", "store": "G07", "suit": "G07"}, {"category": "Designer Fashions & Sportswear", "telephone": "C07", "store": "C07", "suit": "C07"}, {"category": "Designer Fashions & Sportswear", "telephone": "D06", "store": "D06", "suit": "D06"}, {"category": "Designer Fashions & Sportswear", "telephone": "G202", "store": "G202", "suit": "G202"}, {"category": "Designer Fashions & Sportswear", "telephone": "A09", "store": "A09", "suit": "A09"}, {"category": "Designer Fashions & Sportswear", "telephone": "A16", "store": "A16", "suit": "A16"}, {"category": "Designer Fashions & Sportswear", "telephone": "B06", "store": "B06", "suit": "B06"}, {"category": "Designer Fashions & Sportswear", "telephone": "C10", "store": "C10", "suit": "C10"}, {"category": "Designer Fashions & Sportswear", "telephone": "B07`", "store": "B07`", "suit": "B07`"}, {"category": "Designer Fashions & Sportswear", "telephone": "D01", "store": "D01", "suit": "D01"}, {"category": "Designer Fashions & Sportswear", "telephone": "E06", "store": "E06", "suit": "E06"}, {"category": "Designer Fashions & Sportswear", "telephone": "E01", "store": "E01", "suit": "E01"}, {"category": "Designer Fashions & Sportswear", "telephone": "G203", "store": "G203", "suit": "G203"}, {"category": "Designer Fashions & Sportswear", "telephone": "A21", "store": "A21", "suit": "A21"}, {"category": "Designer Fashions & Sportswear", "telephone": "G205", "store": "G205", "suit": "G205"}, {"category": "Designer Fashions & Sportswear", "telephone": "000", "store": "000", "suit": "000"}, {"category": "Designer Fashions & Sportswear", "telephone": "G14", "store": "G14", "suit": "G14"}, {"category": "Designer Fashions & Sportswear", "telephone": "E09", "store": "E09", "suit": "E09"}, {"category": "Designer Fashions & Sportswear", "telephone": "G18", "store": "G18", "suit": "G18"}, {"category": "Designer Fashions & Sportswear", "telephone": "F01", "store": "F01", "suit": "F01"}, {"category": "Designer Fashions & Sportswear", "telephone": "G201", "store": "G201", "suit": "G201"}, {"category": "Designer Fashions & Sportswear", "telephone": "D08", "store": "D08", "suit": "D08"}, {"category": "Designer Fashions & Sportswear", "telephone": "B12", "store": "B12", "suit": "B12"}, {"category": "Designer Fashions & Sportswear", "telephone": "A23", "store": "A23", "suit": "A23"}, {"category": "Designer Fashions & Sportswear", "telephone": "B11", "store": "B11", "suit": "B11"}, {"category": "Designer Fashions & Sportswear", "telephone": "H01B", "store": "H01B", "suit": "H01B"}, {"category": "Designer Fashions & Sportswear", "telephone": "A17", "store": "A17", "suit": "A17"}, {"category": "Designer Fashions & Sportswear", "telephone": "G15", "store": "G15", "suit": "G15"}, {"category": "For Children", "telephone": "G01", "store": "G01", "suit": "G01"}, {"category": "For Children", "telephone": "F00", "store": "F00", "suit": "F00"}, {"category": "For Children", "telephone": "G09", "store": "G09", "suit": "G09"}, {"category": "For Children", "telephone": "E07", "store": "E07", "suit": "E07"}, {"category": "For Children", "telephone": "G203", "store": "G203", "suit": "G203"}, {"category": "For Children", "telephone": "D05", "store": "D05", "suit": "D05"}, {"category": "For Children", "telephone": "B14", "store": "B14", "suit": "B14"}, {"category": "For Children", "telephone": "C13", "store": "C13", "suit": "C13"}, {"category": "For Children", "telephone": "D08", "store": "D08", "suit": "D08"}, {"category": "For Children", "telephone": "B12", "store": "B12", "suit": "B12"}, {"category": "Shoes", "telephone": "D09", "store": "D09", "suit": "D09"}, {"category": "Shoes", "telephone": "C05", "store": "C05", "suit": "C05"}, {"category": "Shoes", "telephone": "G04", "store": "G04", "suit": "G04"}, {"category": "Shoes", "telephone": "E05", "store": "E05", "suit": "E05"}, {"category": "Shoes", "telephone": "G204", "store": "G204", "suit": "G204"}, {"category": "Shoes", "telephone": "G10", "store": "G10", "suit": "G10"}, {"category": "Shoes", "telephone": "A10", "store": "A10", "suit": "A10"}, {"category": "Shoes", "telephone": "H03", "store": "H03", "suit": "H03"}, {"category": "Shoes", "telephone": "G03", "store": "G03", "suit": "G03"}, {"category": "Shoes", "telephone": "A08", "store": "A08", "suit": "A08"}, {"category": "Shoes", "telephone": "F03", "store": "F03", "suit": "F03"}, {"category": "Shoes", "telephone": "G12", "store": "G12", "suit": "G12"}, {"category": "Shoes", "telephone": "G202", "store": "G202", "suit": "G202"}, {"category": "Shoes", "telephone": "A01A", "store": "A01A", "suit": "A01A"}, {"category": "Shoes", "telephone": "000", "store": "000", "suit": "000"}, {"category": "Shoes", "telephone": "G205", "store": "G205", "suit": "G205"}, {"category": "Shoes", "telephone": "A10", "store": "A10", "suit": "A10"}, {"category": "Shoes", "telephone": "G18", "store": "G18", "suit": "G18"}, {"category": "Shoes", "telephone": "G16", "store": "G16", "suit": "G16"}, {"category": "Shoes", "telephone": "D04", "store": "D04", "suit": "D04"}, {"category": "Shoes", "telephone": "C13", "store": "C13", "suit": "C13"}, {"category": "Shoes", "telephone": "G201", "store": "G201", "suit": "G201"}, {"category": "Fine Leather & Luggage", "telephone": "G05", "store": "G05", "suit": "G05"}, {"category": "Fine Leather & Luggage", "telephone": "A03", "store": "A03", "suit": "A03"}, {"category": "Fine Leather & Luggage", "telephone": "A17", "store": "A17", "suit": "A17"}, {"category": "Accessories & Jewelry", "telephone": "B00", "store": "B00", "suit": "B00"}, {"category": "Accessories & Jewelry", "telephone": "E05", "store": "E05", "suit": "E05"}, {"category": "Accessories & Jewelry", "telephone": "C08", "store": "C08", "suit": "C08"}, {"category": "Accessories & Jewelry", "telephone": "A18", "store": "A18", "suit": "A18"}, {"category": "Accessories & Jewelry", "telephone": "A00", "store": "A00", "suit": "A00"}, {"category": "Accessories & Jewelry", "telephone": "B02", "store": "B02", "suit": "B02"}, {"category": "Accessories & Jewelry", "telephone": "E06", "store": "E06", "suit": "E06"}, {"category": "Accessories & Jewelry", "telephone": "B13", "store": "B13", "suit": "B13"}, {"category": "Accessories & Jewelry", "telephone": "H02", "store": "H02", "suit": "H02"}, {"category": "Accessories & Jewelry", "telephone": "G20", "store": "G20", "suit": "G20"}, {"category": "Accessories & Jewelry", "telephone": "G19", "store": "G19", "suit": "G19"}, {"category": "Housewares & Home Furnishings", "telephone": "A15", "store": "A15", "suit": "A15"}, {"category": "Housewares & Home Furnishings", "telephone": "A20", "store": "A20", "suit": "A20"}, {"category": "Housewares & Home Furnishings", "telephone": "F04", "store": "F04", "suit": "F04"}, {"category": "Gifts & Specialty Items", "telephone": "C03", "store": "C03", "suit": "C03"}, {"category": "Gifts & Specialty Items", "telephone": "D07", "store": "D07", "suit": "D07"}, {"category": "Gifts & Specialty Items", "telephone": "F02", "store": "F02", "suit": "F02"}, {"category": "Gifts & Specialty Items", "telephone": "C02", "store": "C02", "suit": "C02"}, {"category": "Gifts & Specialty Items", "telephone": "G-11", "store": "G-11", "suit": "G-11"}, {"category": "Gifts & Specialty Items", "telephone": "B04", "store": "B04", "suit": "B04"}, {"category": "Gifts & Specialty Items", "telephone": "B03", "store": "B03", "suit": "B03"}, {"category": "Gifts & Specialty Items", "telephone": "D03", "store": "D03", "suit": "D03"}, {"category": "Gifts & Specialty Items", "telephone": "C11", "store": "C11", "suit": "C11"}, {"category": "Food", "telephone": "B16", "store": "B16", "suit": "B16"}, {"category": "Food", "telephone": "C01", "store": "C01", "suit": "C01"}, {"category": "Food", "telephone": "C01", "store": "C01", "suit": "C01"}, {"category": "Food", "telephone": "G02", "store": "G02", "suit": "G02"}, {"category": "Food", "telephone": "C01", "store": "C01", "suit": "C01"}, {"category": "Food", "telephone": "C01", "store": "C01", "suit": "C01"}, {"category": "Food", "telephone": "C01", "store": "C01", "suit": "C01"}, {"category": "Food", "telephone": "B15", "store": "B15", "suit": "B15"}, {"category": "Food", "telephone": "E03", "store": "E03", "suit": "E03"}], "address": "1000 Premium Outlets Drive, Tannersville, PA\u00a018372 ", "tel": "(570) 629-4650", "id": "59", "name": "The Crossings Premium Outlets "}